[
  { "id"        : 1,
      "name"      : "PC",
      "alias"     : "pc",
      "icon"      : "pc-1336524756.png",
      "console"   : "1.png",
      "controller": "",
      "developer" : "IBM"
  },
  {
    "id"        : 2,
    "name"      : "PS4",
    "alias"     : "sony-psp",
    "icon"      : "sony-psp-1336525006.png",
    "console"   : "13.png",
    "controller": "13.png",
    "developer" : "Sony"
  },
  {
    "id"        : 3,
    "name"      : "Xbox",
    "alias"     : "xbox-one",
    "icon"      : "sega-dreamcast-1336524794.png",
    "console"   : "16.png",
    "controller": "16.png"
  }
]